OpenAttack/__init__.py
OpenAttack/data_manager.py
OpenAttack/exception.py
OpenAttack/version.py
OpenAttack/attack_assist/__init__.py
OpenAttack/attack_assist/filter_words/__init__.py
OpenAttack/attack_assist/filter_words/chinese.py
OpenAttack/attack_assist/filter_words/english.py
OpenAttack/attack_assist/goal/__init__.py
OpenAttack/attack_assist/goal/base.py
OpenAttack/attack_assist/goal/classifier_goal.py
OpenAttack/attack_assist/substitute/__init__.py
OpenAttack/attack_assist/substitute/char/__init__.py
OpenAttack/attack_assist/substitute/char/base.py
OpenAttack/attack_assist/substitute/char/chinese_fyh_char.py
OpenAttack/attack_assist/substitute/char/chinese_sim_char.py
OpenAttack/attack_assist/substitute/char/english_dces.py
OpenAttack/attack_assist/substitute/char/english_eces.py
OpenAttack/attack_assist/substitute/word/__init__.py
OpenAttack/attack_assist/substitute/word/base.py
OpenAttack/attack_assist/substitute/word/chinese_cilin.py
OpenAttack/attack_assist/substitute/word/chinese_hownet.py
OpenAttack/attack_assist/substitute/word/chinese_word2vec.py
OpenAttack/attack_assist/substitute/word/chinese_wordnet.py
OpenAttack/attack_assist/substitute/word/embed_based.py
OpenAttack/attack_assist/substitute/word/english_counterfit.py
OpenAttack/attack_assist/substitute/word/english_glove.py
OpenAttack/attack_assist/substitute/word/english_hownet.py
OpenAttack/attack_assist/substitute/word/english_word2vec.py
OpenAttack/attack_assist/substitute/word/english_wordnet.py
OpenAttack/attack_assist/word_embedding/__init__.py
OpenAttack/attack_eval/__init__.py
OpenAttack/attack_eval/attack_eval.py
OpenAttack/attack_eval/utils.py
OpenAttack/attackers/__init__.py
OpenAttack/attackers/base.py
OpenAttack/attackers/classification.py
OpenAttack/attackers/bae/__init__.py
OpenAttack/attackers/bert_attack/__init__.py
OpenAttack/attackers/deepwordbug/__init__.py
OpenAttack/attackers/fd/__init__.py
OpenAttack/attackers/gan/__init__.py
OpenAttack/attackers/genetic/__init__.py
OpenAttack-2.1.1.dist-info/LICENSE
OpenAttack-2.1.1.dist-info/METADATA
OpenAttack-2.1.1.dist-info/WHEEL
OpenAttack-2.1.1.dist-info/top_level.txt
OpenAttack-2.1.1.dist-info/RECORD
