Metadata-Version: 2.1
Name: OpenAttack
Version: 2.1.1
Summary: OpenAttack
Home-page: https://github.com/thunlp/OpenAttack
Author: THUNLP
Author-email: thunlp@gmail.com
License: UNKNOWN
Platform: UNKNOWN
Classifier: Programming Language :: Python :: 3
Classifier: License :: OSI Approved :: MIT License
Classifier: Operating System :: OS Independent
Requires-Python: >=3.6
Requires-Dist: nltk (>=3.5)
Requires-Dist: numpy
Requires-Dist: datasets
Requires-Dist: tqdm
Requires-Dist: transformers (>=4.0.0)
Requires-Dist: torch (>=1.5.1)
